sage_x3_requests/__init__.py
internal_lib_48e662a6-0.1.0a6.dist-info/METADATA
internal_lib_48e662a6-0.1.0a6.dist-info/WHEEL
internal_lib_48e662a6-0.1.0a6.dist-info/top_level.txt
internal_lib_48e662a6-0.1.0a6.dist-info/RECORD
