Metadata-Version: 2.4
Name: internal-lib-48e662a6
Version: 0.1.0a6
Summary: Internal utility package
Project-URL: Homepage, https://github.com/seu-usuario/sage_x3_requests
Classifier: Development Status :: 3 - Alpha
Classifier: Intended Audience :: Developers
Classifier: Topic :: Software Development :: Libraries :: Python Modules
Requires-Python: >=3.8
Requires-Dist: httpx
Requires-Dist: pydantic
